tests/__init__.py
tests/test_rest_api.py
wt/__init__.py
wt/pygardena/__init__.py
wt/pygardena/account.py
wt/pygardena/device.py
wt/pygardena/location.py
wt/pygardena/mower.py
wt/pygardena/rest_api.py
wt/pygardena/sensor.py
wt/pygardena/watering_computer.py
wt.pygardena-0.9.6.dist-info/LICENSE
wt.pygardena-0.9.6.dist-info/METADATA
wt.pygardena-0.9.6.dist-info/WHEEL
wt.pygardena-0.9.6.dist-info/top_level.txt
wt.pygardena-0.9.6.dist-info/RECORD
